srcs/ALU.v
`timescale 1ns / 1ps
//////////////////////////////////////////////////////////////////////////////////
// Company: 
// Engineer: 
// 
// Create Date: 11/27/2023 09:04:19 PM
// Design Name: 
// Module Name: ALU
// Project Name: 
// Target Devices: 
// Tool Versions: 
// Description: 
// 
// Dependencies: 
// 
// Revision:
// Revision 0.01 - File Created
// Additional Comments:
// 
//////////////////////////////////////////////////////////////////////////////////


module ALU #(parameter n = 32) (
    input clk, 
    [n-1:0] rs1,  // how to make sure that it's the same n? 
    [n-1:0] rs2,  
    [31:0] inst,
    output reg [n-1:0] res, 
    output reg zf
    );
    wire [6:0] opcode = inst [6:0];
    wire [2:0] func3 = inst[14:12];
    reg [6:0] func7;
    reg [11:0] imm;
        
     always @(posedge clk) begin 
     
     
     
     
        if (opcode == 7'b0110011) begin 
             // R instructions 
             func7 = inst[31:25];
             if (func3 == 3'b000) begin // add and sub 
                    if (func7 == 7'b0) begin 
                        res = rs1 + rs2;
                    end
                    else if (func7 == 7'b0100000) begin 
                        res = rs1 - rs2;
                    end
             end
             if (func3 == 3'b001) begin // SLL
                        res = rs1 << rs2; // check the logic, 
             end
             if (func3 == 3'b010) begin // SLT
                if (rs1 < rs2) begin 
                        res = 1; 
                end 
                else begin
                    res = 0;
                end
             end
             if (func3 == 3'b011) begin // SLTU // recheck
                if ((!rs1 +1) < (!rs2+1)) begin 
                        res = 1; 
                end 
                else begin
                    res = 0;
                end
             end
             if (func3 == 3'b100) begin // XOR
                        res = rs1 ^ rs2; // 
             end
             
             if (func3 == 3'b101) begin // SR
                        if (func7 ==7'b0000000) begin // SRL
                            res = rs1 >> rs2; 
                        end 
                        else if (func7 == 7'b0100000) begin //SRA
                            res = rs1 >>> rs2; 
             end
             end
             if (func3 == 3'b110) begin // OR
                        res = rs1 | rs2; 
             end
             
             if (func3 == 3'b111) begin // AND
                        res = rs1 & rs2; 
             end
        end
        
        
       
        else if (opcode == 7'b0010011) begin
             imm = inst[31:20]; 
             if (func3 == 3'b000) begin // ADDI
                        res = rs1 + imm; 
             end
             
             if (func3 == 3'b010) begin // SLTI
                if (rs1 < imm) begin 
                        res = 1; 
                end 
                else begin
                    res = 0;
                end
             end
             
             if (func3 == 3'b010) begin // SLTIU
                if ((!rs1+1) < (!imm+1)) begin 
                        res = 1; 
                end 
                else begin
                    res = 0;
                end
             end
             
             if (func3 == 3'b100) begin // XORI
                        res = rs1 ^ imm; 
             end
             
             if (func3 == 3'b110) begin // ORI
                        res = rs1 | imm; 
             end
             
             if (func3 == 3'b111) begin // ANDI
                        res = rs1 & imm; 
             end
        end
        
        
        assign zf = (res==0)? 1: 0; // assign zf


end
    
endmodule

src/regFile.v
`timescale 1ns / 1ps
//////////////////////////////////////////////////////////////////////////////////
// Company: 
// Engineer: 
// 
// Create Date: 11/27/2023 08:03:40 PM
// Design Name: Register File
// Module Name: regFile
// Project Name: DD1 Project 2
// Target Devices: 
// Tool Versions: 
// Description: 
// 
// Dependencies: 
// 
// Revision:
// Revision 0.01 - File Created
// Additional Comments:
// 
//////////////////////////////////////////////////////////////////////////////////


module regFile #(parameter n = 32) (  // n-bit regfile 
        input clk,
        rst, 
        regWrite, // flag from CU
        input [4:0]readAddr1, // how many bits ? [4:0] ?
        input [4:0]readAddr2, //
        input [4:0]writeAddr, //
        input [n-1:0] writeData, // 32 bits  [n-1:0]
        output reg [n-1:0] rs1, //  [n-1:0]
        output reg [n-1:0] rs2
    );
    reg [n-1: 0] regFileArr [31:0]; // recheck logic
    integer i;
    initial begin // initialize the regfile with 0's // useless uf testbench starts with rst = 1
        for (i = 0; i < 32; i = i + 1) begin
            regFileArr[i] = 32'b0;
        end
    end 
    
    always @(posedge clk or posedge rst) begin // read operations
        if (rst) begin
          rs1 <= 0; // reset the output if rst
          rs2 <= 0;
        end else begin
          rs1 <= regFileArr[readAddr1];
          rs2 <= regFileArr[readAddr2];
        end
  end
  always @(posedge clk or posedge rst) begin // write operations 
    if (rst) begin
        for (i = 0; i < 32; i = i + 1) begin
            regFileArr[i] <= i; // reset all to zero 
        end
    end else begin
        regFileArr[writeAddr] <= writeData; // write the data unless the address overflows the register array
    end
  end 
     
    
endmodule

src/instMem.v
`timescale 1ns / 1ps
//////////////////////////////////////////////////////////////////////////////////
// Company: 
// Engineer: 
// 
// Create Date: 11/28/2023 01:29:32 PM
// Design Name: 
// Module Name: instMem
// Project Name: 
// Target Devices: 
// Tool Versions: 
// Description: 
// 
// Dependencies: 
// 
// Revision:
// Revision 0.01 - File Created
// Additional Comments:
// 
//////////////////////////////////////////////////////////////////////////////////


module instMem (input [4:0] addr, output [31:0] inst);
reg [31:0] mem [31:0]; // 64 instructions of size 32 bits
 assign inst = mem[addr];
 
    initial begin
         mem[0]=32'b01000000000100011000000010110011 ; //sub x1, x3, x1           x1 = 2
         mem[1]=32'b00000000001000011000000100110011 ; //add x2, x3, x2           x2 = 5 
         mem[2]=32'b00000000000100100001000110110011 ; //sll x3, x4, x1           x3 =12 // check logic 
         mem[3]=32'b00000000011000101010001000110011 ; //slt x4, x5, x6           x4 = 1
         mem[4]=32'b00000000010100110010001010110011; //slt x5, x6, x5            x5 = 0 // retest sltu
         mem[5]=32'b00000000100000111100001100110011 ; //xor x6, x7, x8           x6 = 15
         mem[6]=32'b00000000000100111101001110110011 ; //srl x7, x7, x1           x7 = 1  // retest sra 
         mem[7]=32'b00000000111101000110010000110011; //or x8, x8, x15            x8 = 15
         mem[8]=32'b00000000101001001111010010110011 ; //and x9, x9, x10          x9 = 8
         mem[9]=32'b00000000001001010000010100010011 ; //addi x10, x10, 2         x10 = 12
         mem[10]=32'b00000001111101011010010110010011 ; //slti x11, x11, 31       x11 = 1 // retest sltiu
         mem[11]=32'b00000000101001111100011000010011 ; //xori x12, x15, 10       x12 = 5
         mem[12]=32'b00000000101001111110011010010011 ; //ori x13, x15, 10        x13 = 15
         mem[13]=32'b00000000101001111111011100010011 ; //andi x14, x15, 10       x14 = 10
    end
 

 
endmodule

srcs/cu.v
module ControlUnit (
  input [6:2] opcode,
  output reg Branch, MemRead, MemtoReg, MemWrite, ALUSrc, RegWrite,
  output reg [1:0] ALUOp
);

  // Default assignments
  always @* begin
    Branch   = 0;
    MemRead  = 0;
    MemtoReg = 0;
    MemWrite = 0;
    ALUSrc   = 0;
    RegWrite = 0;
    ALUOp    = 2'b00; // goes to alu ctrl 

    // Decode opcode
    case (opcode)
      5'b01100: begin // R-Type
        RegWrite = 1;
        ALUOp    = 2'b10;
      end

      5'b00100: begin // I-Type
        MemRead  = 1;
        MemtoReg = 1;
        ALUSrc   = 1;
        RegWrite = 1;
        ALUOp    = 2'b11;
      end

      5'b01000: begin // S-Type
        MemWrite = 1;
        ALUSrc   = 1;
        ALUOp    = 2'b00;
      end

      5'b11000: begin //Branch
        Branch = 1;
        ALUOp  = 2'b01;
      end
    endcase
  end

endmodule

src/driver.v
`timescale 1ns / 1ps
`include "../src/instMem.v"
`include "../src/ALU.v"
`include "../src/regFile.v"
`include "../src/cu.v"
//////////////////////////////////////////////////////////////////////////////////
// Company: 
// Engineer: 
// 
// Create Date: 11/27/2023 11:20:55 PM
// Design Name: 
// Module Name: driver
// Project Name: 
// Target Devices: 
// Tool Versions: 
// Description: 
// 
// Dependencies: 
// 
// Revision:
// Revision 0.01 - File Created
// Additional Comments:
// 
//////////////////////////////////////////////////////////////////////////////////


module driver(
    input clk,
    rst,
    regWrite,
    input [4:0] instAddr
);
    wire [31:0] rs1;
    wire [31:0] rs2;
    wire [31:0] res;
    wire [31:0] inst;
    wire zf;
    wire branch;
    wire MemRead;
    wire MemtoReg;
    wire MemWrite;
    wire ALUSrc;
    wire [0:1] ALUOp;
    ControlUnit cu (
    .opcode(inst[6:2]),
    .Branch(Branch),
    .MemRead(MemRead),
    .MemtoReg(MemtoReg),
    .MemWrite(MemWrite),
    .ALUSrc(ALUSrc),
    .RegWrite(regWrite),
    .ALUOp(ALUOp)
  );
    instMem insts(.addr(instAddr), .inst(inst));
    regFile reg1 (.clk(clk), .rst(rst), .regWrite(regWrite), .readAddr1(inst[19:15]), .readAddr2(inst[24:20]),.writeAddr(inst[11:7]), .writeData(res), .rs1(rs1), .rs2(rs2));   
    ALU alu1 ( .clk(clk), .rs1(rs1), .rs2(rs2), .inst(inst), .res(res), .zf(zf));
  
    
    
endmodule

simulations/tb.v
`timescale 1ns / 1ps
`include "../src/driver.v"
//////////////////////////////////////////////////////////////////////////////////
// Company: 
// Engineer: 
// 
// Create Date: 11/27/2023 11:23:16 PM
// Design Name: 
// Module Name: tb
// Project Name: 
// Target Devices: 
// Tool Versions: 
// Description: 
// 
// Dependencies: 
// 
// Revision:
// Revision 0.01 - File Created
// Additional Comments:
// 
//////////////////////////////////////////////////////////////////////////////////


module tb();
    localparam period = 1000;
    reg clk, rst, regWrite;
    reg [4:0] instAddr;
    initial begin
        clk = 1'b0;
        forever begin
        #50 clk = ~clk;
        end 
    end
    driver driver2(.clk(clk), .rst(rst),.regWrite(regWrite), .instAddr(instAddr));

    initial begin
        $dumpfile("tb.vcd");
        $dumpvars(0, tb);
        rst =1; 
        #period
        rst=0;
        #period
        instAddr = 0; 
        #period
        instAddr = 1; 
        #period
        instAddr = 2; 
        #period
        instAddr = 3; 
        #period
        instAddr = 4; 
        #period
        instAddr = 5; 
        #period
        instAddr = 6; 
        #period
        instAddr = 7; 
        #period
        instAddr = 8; 
        #period
        instAddr = 9; 
        #period
        instAddr = 10; 
        #period
        instAddr = 11; 
        #period
        instAddr = 12; 
        #period
        instAddr = 13; 
        $finish;
    end

endmodule

simulations/tb.vcd
$date
	Tue Nov 28 16:22:45 2023
$end
$version
	Icarus Verilog
$end
$timescale
	1ps
$end
$scope module tb $end
$var parameter 32 ! period $end
$var reg 1 " clk $end
$var reg 5 # instAddr [4:0] $end
$var reg 1 $ regWrite $end
$var reg 1 % rst $end
$scope module driver2 $end
$var wire 1 " clk $end
$var wire 5 & instAddr [4:0] $end
$var wire 1 ' regWrite $end
$var wire 1 % rst $end
$var wire 1 ( zf $end
$var wire 32 ) rs2 [31:0] $end
$var wire 32 * rs1 [31:0] $end
$var wire 32 + res [31:0] $end
$var wire 32 , inst [31:0] $end
$var wire 1 - MemtoReg $end
$var wire 1 . MemWrite $end
$var wire 1 / MemRead $end
$var wire 1 0 Branch $end
$var wire 1 1 ALUSrc $end
$var wire 2 2 ALUOp [0:1] $end
$scope module alu1 $end
$var wire 1 " clk $end
$var wire 32 3 rs2 [31:0] $end
$var wire 32 4 rs1 [31:0] $end
$var wire 7 5 opcode [6:0] $end
$var wire 32 6 inst [31:0] $end
$var wire 3 7 func3 [2:0] $end
$var parameter 32 8 n $end
$var reg 7 9 func7 [6:0] $end
$var reg 12 : imm [11:0] $end
$var reg 32 ; res [31:0] $end
$var reg 1 ( zf $end
$upscope $end
$scope module cu $end
$var wire 5 < opcode [6:2] $end
$var reg 2 = ALUOp [1:0] $end
$var reg 1 1 ALUSrc $end
$var reg 1 0 Branch $end
$var reg 1 / MemRead $end
$var reg 1 . MemWrite $end
$var reg 1 - MemtoReg $end
$var reg 1 > RegWrite $end
$upscope $end
$scope module insts $end
$var wire 5 ? addr [4:0] $end
$var wire 32 @ inst [31:0] $end
$upscope $end
$scope module reg1 $end
$var wire 1 " clk $end
$var wire 5 A readAddr1 [4:0] $end
$var wire 5 B readAddr2 [4:0] $end
$var wire 1 ' regWrite $end
$var wire 1 % rst $end
$var wire 5 C writeAddr [4:0] $end
$var wire 32 D writeData [31:0] $end
$var parameter 32 E n $end
$var reg 32 F rs1 [31:0] $end
$var reg 32 G rs2 [31:0] $end
$var integer 32 H i [31:0] $end
$upscope $end
$upscope $end
$upscope $end
$enddefinitions $end
$comment Show the parameter values. $end
$dumpall
b100000 E
b100000 8
b1111101000 !
$end
#0
$dumpvars
b100000 H
b0 G
b0 F
bx D
bx C
bx B
bx A
bx @
bx ?
x>
bx =
bx <
bx ;
bx :
bx 9
bx 7
bx 6
bx 5
b0 4
b0 3
bx 2
x1
x0
x/
x.
x-
bx ,
bx +
b0 *
b0 )
x(
x'
bx &
1%
x$
bx #
0"
$end
#50000
b100000 H
1"
#100000
0"
#150000
b100000 H
1"
#200000
0"
#250000
b100000 H
1"
#300000
0"
#350000
b100000 H
1"
#400000
0"
#450000
b100000 H
1"
#500000
0"
#550000
b100000 H
1"
#600000
0"
#650000
b100000 H
1"
#700000
0"
#750000
b100000 H
1"
#800000
0"
#850000
b100000 H
1"
#900000
0"
#950000
b100000 H
1"
#1000000
0"
0%
#1050000
bx )
bx 3
bx G
bx *
bx 4
bx F
1"
#1100000
0"
#1150000
1"
#1200000
0"
#1250000
1"
#1300000
0"
#1350000
1"
#1400000
0"
#1450000
1"
#1500000
0"
#1550000
1"
#1600000
0"
#1650000
1"
#1700000
0"
#1750000
1"
#1800000
0"
#1850000
1"
#1900000
0"
#1950000
1"
#2000000
b10 2
b10 =
1>
01
0.
0-
0/
00
b0 7
b110011 5
b1 C
b1 B
b11 A
b1100 <
0"
b1000000000100011000000010110011 ,
b1000000000100011000000010110011 6
b1000000000100011000000010110011 @
b0 #
b0 &
b0 ?
#2050000
b1 )
b1 3
b1 G
b11 *
b11 4
b11 F
b100000 9
1"
#2100000
0"
#2150000
bx )
bx 3
bx G
0(
b10 +
b10 ;
b10 D
1"
#2200000
0"
#2250000
x(
bx +
bx ;
bx D
1"
#2300000
0"
#2350000
b10 )
b10 3
b10 G
1"
#2400000
0"
#2450000
bx )
bx 3
bx G
0(
b1 +
b1 ;
b1 D
1"
#2500000
0"
#2550000
x(
bx +
bx ;
bx D
1"
#2600000
0"
#2650000
b1 )
b1 3
b1 G
1"
#2700000
0"
#2750000
bx )
bx 3
bx G
0(
b10 +
b10 ;
b10 D
1"
#2800000
0"
#2850000
x(
bx +
bx ;
bx D
1"
#2900000
0"
#2950000
b10 )
b10 3
b10 G
1"
#3000000
b10 C
b10 B
0"
b1000011000000100110011 ,
b1000011000000100110011 6
b1000011000000100110011 @
b1 #
b1 &
b1 ?
#3050000
0(
b101 +
b101 ;
b101 D
b0 9
1"
#3100000
0"
#3150000
bx )
bx 3
bx G
1"
#3200000
0"
#3250000
b101 )
b101 3
b101 G
x(
bx +
bx ;
bx D
1"
#3300000
0"
#3350000
0(
b1000 +
b1000 ;
b1000 D
1"
#3400000
0"
#3450000
bx )
bx 3
bx G
1"
#3500000
0"
#3550000
b1000 )
b1000 3
b1000 G
x(
bx +
bx ;
bx D
1"
#3600000
0"
#3650000
0(
b1011 +
b1011 ;
b1011 D
1"
#3700000
0"
#3750000
bx )
bx 3
bx G
1"
#3800000
0"
#3850000
b1011 )
b1011 3
b1011 G
x(
bx +
bx ;
bx D
1"
#3900000
0"
#3950000
0(
b1110 +
b1110 ;
b1110 D
1"
#4000000
b1 7
b11 C
b1 B
b100 A
0"
b100100001000110110011 ,
b100100001000110110011 6
b100100001000110110011 @
b10 #
b10 &
b10 ?
#4050000
bx )
bx 3
bx G
b100 *
b100 4
b100 F
b1100000000000 +
b1100000000000 ;
b1100000000000 D
1"
#4100000
0"
#4150000
x(
bx +
bx ;
bx D
1"
#4200000
0"
#4250000
1"
#4300000
0"
#4350000
1"
#4400000
0"
#4450000
1"
#4500000
0"
#4550000
1"
#4600000
0"
#4650000
1"
#4700000
0"
#4750000
1"
#4800000
0"
#4850000
1"
#4900000
0"
#4950000
1"
#5000000
b10 7
b100 C
b110 B
b101 A
0"
b11000101010001000110011 ,
b11000101010001000110011 6
b11000101010001000110011 @
b11 #
b11 &
b11 ?
#5050000
b110 )
b110 3
b110 G
b101 *
b101 4
b101 F
1(
b0 +
b0 ;
b0 D
1"
#5100000
0"
#5150000
0(
b1 +
b1 ;
b1 D
1"
#5200000
0"
#5250000
1"
#5300000
0"
#5350000
1"
#5400000
0"
#5450000
1"
#5500000
0"
#5550000
1"
#5600000
0"
#5650000
1"
#5700000
0"
#5750000
1"
#5800000
0"
#5850000
1"
#5900000
0"
#5950000
1"
#6000000
b101 C
b101 B
b110 A
0"
b10100110010001010110011 ,
b10100110010001010110011 6
b10100110010001010110011 @
b100 #
b100 &
b100 ?
#6050000
b101 )
b101 3
b101 G
b110 *
b110 4
b110 F
1"
#6100000
0"
#6150000
b1 )
b1 3
b1 G
1(
b0 +
b0 ;
b0 D
1"
#6200000
0"
#6250000
1"
#6300000
0"
#6350000
b0 )
b0 3
b0 G
1"
#6400000
0"
#6450000
1"
#6500000
0"
#6550000
1"
#6600000
0"
#6650000
1"
#6700000
0"
#6750000
1"
#6800000
0"
#6850000
1"
#6900000
0"
#6950000
1"
#7000000
b100 7
b110 C
b1000 B
b111 A
0"
b100000111100001100110011 ,
b100000111100001100110011 6
b100000111100001100110011 @
b101 #
b101 &
b101 ?
#7050000
b1000 )
b1000 3
b1000 G
b111 *
b111 4
b111 F
0(
b110 +
b110 ;
b110 D
1"
#7100000
0"
#7150000
b1111 +
b1111 ;
b1111 D
1"
#7200000
0"
#7250000
1"
#7300000
0"
#7350000
1"
#7400000
0"
#7450000
1"
#7500000
0"
#7550000
1"
#7600000
0"
#7650000
1"
#7700000
0"
#7750000
1"
#7800000
0"
#7850000
1"
#7900000
0"
#7950000
1"
#8000000
b101 7
b111 C
b1 B
0"
b100111101001110110011 ,
b100111101001110110011 6
b100111101001110110011 @
b110 #
b110 &
b110 ?
#8050000
bx )
bx 3
bx G
1(
b0 +
b0 ;
b0 D
1"
#8100000
0"
#8150000
b1111 *
b1111 4
b1111 F
x(
bx +
bx ;
bx D
1"
#8200000
0"
#8250000
b0 *
b0 4
b0 F
1"
#8300000
0"
#8350000
bx *
bx 4
bx F
1"
#8400000
0"
#8450000
1"
#8500000
0"
#8550000
1"
#8600000
0"
#8650000
1"
#8700000
0"
#8750000
1"
#8800000
0"
#8850000
1"
#8900000
0"
#8950000
1"
#9000000
b110 7
b1000 C
b1111 B
b1000 A
0"
b111101000110010000110011 ,
b111101000110010000110011 6
b111101000110010000110011 @
b111 #
b111 &
b111 ?
#9050000
b1111 )
b1111 3
b1111 G
b1000 *
b1000 4
b1000 F
1"
#9100000
0"
#9150000
bx *
bx 4
bx F
0(
b1111 +
b1111 ;
b1111 D
1"
#9200000
0"
#9250000
bx1111 +
bx1111 ;
bx1111 D
1"
#9300000
0"
#9350000
b1111 *
b1111 4
b1111 F
1"
#9400000
0"
#9450000
bx1111 *
bx1111 4
bx1111 F
b1111 +
b1111 ;
b1111 D
1"
#9500000
0"
#9550000
bx1111 +
bx1111 ;
bx1111 D
1"
#9600000
0"
#9650000
b1111 *
b1111 4
b1111 F
1"
#9700000
0"
#9750000
bx1111 *
bx1111 4
bx1111 F
b1111 +
b1111 ;
b1111 D
1"
#9800000
0"
#9850000
bx1111 +
bx1111 ;
bx1111 D
1"
#9900000
0"
#9950000
b1111 *
b1111 4
b1111 F
1"
#10000000
b111 7
b1001 C
b1010 B
b1001 A
0"
b101001001111010010110011 ,
b101001001111010010110011 6
b101001001111010010110011 @
b1000 #
b1000 &
b1000 ?
#10050000
b1010 )
b1010 3
b1010 G
b1001 *
b1001 4
b1001 F
b1111 +
b1111 ;
b1111 D
1"
#10100000
0"
#10150000
bx1111 *
bx1111 4
bx1111 F
b1000 +
b1000 ;
b1000 D
1"
#10200000
0"
#10250000
b1111 *
b1111 4
b1111 F
b1010 +
b1010 ;
b1010 D
1"
#10300000
0"
#10350000
b1000 *
b1000 4
b1000 F
1"
#10400000
0"
#10450000
b1010 *
b1010 4
b1010 F
b1000 +
b1000 ;
b1000 D
1"
#10500000
0"
#10550000
b1010 +
b1010 ;
b1010 D
1"
#10600000
0"
#10650000
b1000 *
b1000 4
b1000 F
1"
#10700000
0"
#10750000
b1010 *
b1010 4
b1010 F
b1000 +
b1000 ;
b1000 D
1"
#10800000
0"
#10850000
b1010 +
b1010 ;
b1010 D
1"
#10900000
0"
#10950000
b1000 *
b1000 4
b1000 F
1"
#11000000
b0 2
b0 =
0>
b0 7
b10011 5
b1010 C
b10 B
b1010 A
b100 <
0"
b1001010000010100010011 ,
b1001010000010100010011 6
b1001010000010100010011 @
b1001 #
b1001 &
b1001 ?
#11050000
bx )
bx 3
bx G
b1010 *
b1010 4
b1010 F
b10 :
1"
#11100000
0"
#11150000
b1100 +
b1100 ;
b1100 D
1"
#11200000
0"
#11250000
1"
#11300000
0"
#11350000
b1100 *
b1100 4
b1100 F
1"
#11400000
0"
#11450000
b1110 +
b1110 ;
b1110 D
1"
#11500000
0"
#11550000
1"
#11600000
0"
#11650000
b1110 *
b1110 4
b1110 F
1"
#11700000
0"
#11750000
b10000 +
b10000 ;
b10000 D
1"
#11800000
0"
#11850000
1"
#11900000
0"
#11950000
b10000 *
b10000 4
b10000 F
1"
#12000000
b10 7
b1011 C
b11111 B
b1011 A
0"
b1111101011010010110010011 ,
b1111101011010010110010011 6
b1111101011010010110010011 @
b1010 #
b1010 &
b1010 ?
#12050000
b11111 )
b11111 3
b11111 G
b1011 *
b1011 4
b1011 F
1(
b0 +
b0 ;
b0 D
b11111 :
1"
#12100000
0"
#12150000
b10000 *
b10000 4
b10000 F
b0 +
b0 ;
b0 D
1"
#12200000
0"
#12250000
b0 *
b0 4
b0 F
b0 +
b0 ;
b0 D
1"
#12300000
0"
#12350000
b0 +
b0 ;
b0 D
1"
#12400000
0"
#12450000
b0 +
b0 ;
b0 D
1"
#12500000
0"
#12550000
b0 +
b0 ;
b0 D
1"
#12600000
0"
#12650000
b0 +
b0 ;
b0 D
1"
#12700000
0"
#12750000
b0 +
b0 ;
b0 D
1"
#12800000
0"
#12850000
b0 +
b0 ;
b0 D
1"
#12900000
0"
#12950000
b0 +
b0 ;
b0 D
1"
#13000000
b100 7
b1100 C
b1010 B
b1111 A
0"
b101001111100011000010011 ,
b101001111100011000010011 6
b101001111100011000010011 @
b1011 #
b1011 &
b1011 ?
#13050000
b10000 )
b10000 3
b10000 G
b1111 *
b1111 4
b1111 F
0(
b1010 +
b1010 ;
b1010 D
b1010 :
1"
#13100000
0"
#13150000
b101 +
b101 ;
b101 D
1"
#13200000
0"
#13250000
1"
#13300000
0"
#13350000
1"
#13400000
0"
#13450000
1"
#13500000
0"
#13550000
1"
#13600000
0"
#13650000
1"
#13700000
0"
#13750000
1"
#13800000
0"
#13850000
1"
#13900000
0"
#13950000
1"
#14000000
b110 7
b1101 C
0"
b101001111110011010010011 ,
b101001111110011010010011 6
b101001111110011010010011 @
b1100 #
b1100 &
b1100 ?
#14050000
b1111 +
b1111 ;
b1111 D
1"
#14100000
0"
#14150000
1"
#14200000
0"
#14250000
1"
#14300000
0"
#14350000
1"
#14400000
0"
#14450000
1"
#14500000
0"
#14550000
1"
#14600000
0"
#14650000
1"
#14700000
0"
#14750000
1"
#14800000
0"
#14850000
1"
#14900000
0"
#14950000
1"
#15000000
b111 7
b1110 C
0"
b101001111111011100010011 ,
b101001111111011100010011 6
b101001111111011100010011 @
b1101 #
b1101 &
b1101 ?
